{
  "version": "6",
  "dialect": "sqlite",
  "id": "546ee729-7c1f-4285-853f-727661869f0b",
  "prevId": "1b2fb96e-b1f1-4f10-a4b9-291dce58d7ca",
  "tables": {
    "Authors": {
      "name": "Authors",
      "columns": {
        "userId": {
          "name": "userId",
          "type": "text",
          "primaryKey": true,
          "notNull": true,
          "autoincrement": false
        },
        "bio": {
          "name": "bio",
          "type": "text",
          "primaryKey": false,
          "notNull": false,
          "autoincrement": false
        }
      },
      "indexes": {
        "Authors_userId_unique": {
          "name": "Authors_userId_unique",
          "columns": [
            "userId"
          ],
          "isUnique": true
        }
      },
      "foreignKeys": {
        "Authors_userId_Users_id_fk": {
          "name": "Authors_userId_Users_id_fk",
          "tableFrom": "Authors",
          "tableTo": "Users",
          "columnsFrom": [
            "userId"
          ],
          "columnsTo": [
            "id"
          ],
          "onDelete": "no action",
          "onUpdate": "no action"
        }
      },
      "compositePrimaryKeys": {},
      "uniqueConstraints": {}
    },
    "Images": {
      "name": "Images",
      "columns": {
        "id": {
          "name": "id",
          "type": "integer",
          "primaryKey": true,
          "notNull": true,
          "autoincrement": true
        },
        "filename": {
          "name": "filename",
          "type": "text",
          "primaryKey": false,
          "notNull": true,
          "autoincrement": false
        },
        "alt": {
          "name": "alt",
          "type": "text",
          "primaryKey": false,
          "notNull": false,
          "autoincrement": false
        },
        "context": {
          "name": "context",
          "type": "text",
          "primaryKey": false,
          "notNull": true,
          "autoincrement": false
        },
        "path": {
          "name": "path",
          "type": "text",
          "primaryKey": false,
          "notNull": true,
          "autoincrement": false
        }
      },
      "indexes": {},
      "foreignKeys": {},
      "compositePrimaryKeys": {},
      "uniqueConstraints": {}
    },
    "PostsAuthors": {
      "name": "PostsAuthors",
      "columns": {
        "postId": {
          "name": "postId",
          "type": "integer",
          "primaryKey": false,
          "notNull": true,
          "autoincrement": false
        },
        "authorId": {
          "name": "authorId",
          "type": "integer",
          "primaryKey": false,
          "notNull": true,
          "autoincrement": false
        }
      },
      "indexes": {},
      "foreignKeys": {
        "PostsAuthors_postId_Posts_id_fk": {
          "name": "PostsAuthors_postId_Posts_id_fk",
          "tableFrom": "PostsAuthors",
          "tableTo": "Posts",
          "columnsFrom": [
            "postId"
          ],
          "columnsTo": [
            "id"
          ],
          "onDelete": "no action",
          "onUpdate": "no action"
        },
        "PostsAuthors_authorId_Authors_userId_fk": {
          "name": "PostsAuthors_authorId_Authors_userId_fk",
          "tableFrom": "PostsAuthors",
          "tableTo": "Authors",
          "columnsFrom": [
            "authorId"
          ],
          "columnsTo": [
            "userId"
          ],
          "onDelete": "no action",
          "onUpdate": "no action"
        }
      },
      "compositePrimaryKeys": {
        "PostsAuthors_postId_authorId_pk": {
          "columns": [
            "authorId",
            "postId"
          ],
          "name": "PostsAuthors_postId_authorId_pk"
        }
      },
      "uniqueConstraints": {}
    },
    "PostsTags": {
      "name": "PostsTags",
      "columns": {
        "postId": {
          "name": "postId",
          "type": "integer",
          "primaryKey": false,
          "notNull": true,
          "autoincrement": false
        },
        "tagName": {
          "name": "tagName",
          "type": "integer",
          "primaryKey": false,
          "notNull": true,
          "autoincrement": false
        }
      },
      "indexes": {},
      "foreignKeys": {
        "PostsTags_postId_Posts_id_fk": {
          "name": "PostsTags_postId_Posts_id_fk",
          "tableFrom": "PostsTags",
          "tableTo": "Posts",
          "columnsFrom": [
            "postId"
          ],
          "columnsTo": [
            "id"
          ],
          "onDelete": "no action",
          "onUpdate": "no action"
        },
        "PostsTags_tagName_Tags_name_fk": {
          "name": "PostsTags_tagName_Tags_name_fk",
          "tableFrom": "PostsTags",
          "tableTo": "Tags",
          "columnsFrom": [
            "tagName"
          ],
          "columnsTo": [
            "name"
          ],
          "onDelete": "no action",
          "onUpdate": "no action"
        }
      },
      "compositePrimaryKeys": {
        "PostsTags_postId_tagName_pk": {
          "columns": [
            "postId",
            "tagName"
          ],
          "name": "PostsTags_postId_tagName_pk"
        }
      },
      "uniqueConstraints": {}
    },
    "Posts": {
      "name": "Posts",
      "columns": {
        "id": {
          "name": "id",
          "type": "integer",
          "primaryKey": true,
          "notNull": true,
          "autoincrement": true
        },
        "slug": {
          "name": "slug",
          "type": "text",
          "primaryKey": false,
          "notNull": true,
          "autoincrement": false
        },
        "topicTitle": {
          "name": "topicTitle",
          "type": "integer",
          "primaryKey": false,
          "notNull": false,
          "autoincrement": false
        },
        "bannerImageId": {
          "name": "bannerImageId",
          "type": "integer",
          "primaryKey": false,
          "notNull": false,
          "autoincrement": false
        },
        "createdAt": {
          "name": "createdAt",
          "type": "integer",
          "primaryKey": false,
          "notNull": true,
          "autoincrement": false
        },
        "updatedAt": {
          "name": "updatedAt",
          "type": "integer",
          "primaryKey": false,
          "notNull": true,
          "autoincrement": false
        },
        "publishedAt": {
          "name": "publishedAt",
          "type": "integer",
          "primaryKey": false,
          "notNull": false,
          "autoincrement": false
        },
        "deletedAt": {
          "name": "deletedAt",
          "type": "integer",
          "primaryKey": false,
          "notNull": false,
          "autoincrement": false
        }
      },
      "indexes": {
        "Posts_slug_unique": {
          "name": "Posts_slug_unique",
          "columns": [
            "slug"
          ],
          "isUnique": true
        }
      },
      "foreignKeys": {
        "Posts_topicTitle_Topics_title_fk": {
          "name": "Posts_topicTitle_Topics_title_fk",
          "tableFrom": "Posts",
          "tableTo": "Topics",
          "columnsFrom": [
            "topicTitle"
          ],
          "columnsTo": [
            "title"
          ],
          "onDelete": "no action",
          "onUpdate": "no action"
        },
        "Posts_bannerImageId_Images_id_fk": {
          "name": "Posts_bannerImageId_Images_id_fk",
          "tableFrom": "Posts",
          "tableTo": "Images",
          "columnsFrom": [
            "bannerImageId"
          ],
          "columnsTo": [
            "id"
          ],
          "onDelete": "no action",
          "onUpdate": "no action"
        }
      },
      "compositePrimaryKeys": {},
      "uniqueConstraints": {}
    },
    "Tags": {
      "name": "Tags",
      "columns": {
        "name": {
          "name": "name",
          "type": "text",
          "primaryKey": true,
          "notNull": true,
          "autoincrement": false
        }
      },
      "indexes": {
        "Tags_name_unique": {
          "name": "Tags_name_unique",
          "columns": [
            "name"
          ],
          "isUnique": true
        }
      },
      "foreignKeys": {},
      "compositePrimaryKeys": {},
      "uniqueConstraints": {}
    },
    "Topics": {
      "name": "Topics",
      "columns": {
        "title": {
          "name": "title",
          "type": "text",
          "primaryKey": true,
          "notNull": true,
          "autoincrement": false
        },
        "imageId": {
          "name": "imageId",
          "type": "integer",
          "primaryKey": false,
          "notNull": false,
          "autoincrement": false
        },
        "slug": {
          "name": "slug",
          "type": "text",
          "primaryKey": false,
          "notNull": true,
          "autoincrement": false
        }
      },
      "indexes": {
        "Topics_title_unique": {
          "name": "Topics_title_unique",
          "columns": [
            "title"
          ],
          "isUnique": true
        },
        "Topics_slug_unique": {
          "name": "Topics_slug_unique",
          "columns": [
            "slug"
          ],
          "isUnique": true
        }
      },
      "foreignKeys": {
        "Topics_title_Tags_name_fk": {
          "name": "Topics_title_Tags_name_fk",
          "tableFrom": "Topics",
          "tableTo": "Tags",
          "columnsFrom": [
            "title"
          ],
          "columnsTo": [
            "name"
          ],
          "onDelete": "no action",
          "onUpdate": "no action"
        },
        "Topics_imageId_Images_id_fk": {
          "name": "Topics_imageId_Images_id_fk",
          "tableFrom": "Topics",
          "tableTo": "Images",
          "columnsFrom": [
            "imageId"
          ],
          "columnsTo": [
            "id"
          ],
          "onDelete": "no action",
          "onUpdate": "no action"
        }
      },
      "compositePrimaryKeys": {},
      "uniqueConstraints": {}
    },
    "Users": {
      "name": "Users",
      "columns": {
        "id": {
          "name": "id",
          "type": "text",
          "primaryKey": true,
          "notNull": true,
          "autoincrement": false
        },
        "username": {
          "name": "username",
          "type": "text",
          "primaryKey": false,
          "notNull": true,
          "autoincrement": false
        },
        "email": {
          "name": "email",
          "type": "text",
          "primaryKey": false,
          "notNull": true,
          "autoincrement": false
        },
        "name": {
          "name": "name",
          "type": "text",
          "primaryKey": false,
          "notNull": true,
          "autoincrement": false
        },
        "lastName": {
          "name": "lastName",
          "type": "text",
          "primaryKey": false,
          "notNull": false,
          "autoincrement": false
        }
      },
      "indexes": {
        "Users_id_unique": {
          "name": "Users_id_unique",
          "columns": [
            "id"
          ],
          "isUnique": true
        },
        "Users_username_unique": {
          "name": "Users_username_unique",
          "columns": [
            "username"
          ],
          "isUnique": true
        },
        "Users_email_unique": {
          "name": "Users_email_unique",
          "columns": [
            "email"
          ],
          "isUnique": true
        }
      },
      "foreignKeys": {},
      "compositePrimaryKeys": {},
      "uniqueConstraints": {}
    }
  },
  "enums": {},
  "_meta": {
    "schemas": {},
    "tables": {},
    "columns": {}
  },
  "internal": {
    "indexes": {}
  }
}